fastapi_dishka/__init__.py
fastapi_dishka/app.py
fastapi_dishka/middleware.py
fastapi_dishka/providers.py
fastapi_dishka/py.typed
fastapi_dishka/router.py
fastapi_dishka-0.2.4.dist-info/licenses/LICENSE
fastapi_dishka-0.2.4.dist-info/METADATA
fastapi_dishka-0.2.4.dist-info/WHEEL
fastapi_dishka-0.2.4.dist-info/top_level.txt
fastapi_dishka-0.2.4.dist-info/RECORD
