Metadata-Version: 2.4
Name: fastapi_dishka
Version: 0.2.4
Summary: FastAPI + Dishka with providers being first-class citizens
Author-email: NSX Team <heynemann@gmail.com>
License: MIT
Project-URL: Homepage, https://github.com/NSXBet/fastapi-dishka
Project-URL: Bug Reports, https://github.com/NSXBet/fastapi-dishka/issues
Project-URL: Source, https://github.com/NSXBet/fastapi-dishka
Classifier: Development Status :: 4 - Beta
Classifier: Intended Audience :: Developers
Classifier: License :: OSI Approved :: MIT License
Classifier: Typing :: Typed
Classifier: Programming Language :: Python :: 3
Classifier: Programming Language :: Python :: 3.13
Classifier: Framework :: AsyncIO
Classifier: Framework :: FastAPI
Classifier: Intended Audience :: Developers
Classifier: Topic :: Software Development :: Libraries
Classifier: Topic :: Software Development :: Libraries :: Python Modules
Requires-Python: >=3.13
License-File: LICENSE
Requires-Dist: dishka>=1.3.0
Requires-Dist: fastapi>=0.115.6
Requires-Dist: uvicorn>=0.32.0
Requires-Dist: structlog>=24.1.0
Provides-Extra: dev
Requires-Dist: pytest>=7.4.0; extra == "dev"
Requires-Dist: pytest-mock>=3.12.0; extra == "dev"
Requires-Dist: pytest-cov>=4.1.0; extra == "dev"
Requires-Dist: pytest-asyncio>=0.21.0; extra == "dev"
Requires-Dist: httpx>=0.24.0; extra == "dev"
Requires-Dist: black>=25.1.0; extra == "dev"
Requires-Dist: isort>=6.0.1; extra == "dev"
Requires-Dist: flake8>=6.1.0; extra == "dev"
Requires-Dist: pyproject-flake8>=7.0.0; extra == "dev"
Requires-Dist: mypy>=1.16.1; extra == "dev"
Requires-Dist: mkdocs-material>=9.4.0; extra == "dev"
Requires-Dist: mkdocstrings[python]>=0.24.0; extra == "dev"
Requires-Dist: ruff>=0.12.0; extra == "dev"
Dynamic: license-file
